[
  {
    "id": 2,
    "title": "Выбор идеального семейного автомобиля!",
    "body": "Сравниваем минивэны, кроссоверы и седаны. Что удобнее для семьи и дальних поездок."
  },
  {
    "id": 3,
    "title": "Электромобили 2025 года: чего ожидать",
    "body": "Обзор новинок электрических автомобилей, их дальность хода, зарядные станции и цены."
  },
  {
    "id": 4,
    "title": "Лучшие автомобильные маршруты Европы",
    "body": "Идеи для путешествий на машине по Италии, Франции и Германии. Красивейшие дороги и места для остановки."
  },
  {
    "id": 5,
    "title": "Как подготовить авто к зиме",
    "body": "Советы по замене шин, проверке аккумулятора и подготовке двигателя к холодному сезону."
  },
  {
    "id": 6,
    "title": "Классические автомобили: ностальгия на колёсах",
    "body": "Обзор ретро-автомобилей, выставки и советы по реставрации классических машин."
  },
  {
    "id": 7,
    "title": "Долгие поездки: комфорт и безопасность",
    "body": "Как сделать дальние поездки на автомобиле комфортными для всей семьи."
  },
  {
    "id": 8,
    "title": "Автомобильные гаджеты 2025",
    "body": "Смарт-системы, камеры, ассистенты парковки и другие технологические новинки для авто."
  }
]